django_pagination_bootstrap/__init__.py
django_pagination_bootstrap/middleware.py
django_pagination_bootstrap/paginator.py
django_pagination_bootstrap/templates/pagination.html
django_pagination_bootstrap/templatetags/__init__.py
django_pagination_bootstrap/templatetags/pagination_tags.py
django_pagination_bootstrap-2.4.5.dist-info/LICENSE
django_pagination_bootstrap-2.4.5.dist-info/WHEEL
django_pagination_bootstrap-2.4.5.dist-info/METADATA
django_pagination_bootstrap-2.4.5.dist-info/RECORD
