Metadata-Version: 2.1
Name: django-pagination-bootstrap
Version: 2.4.5
Summary: Easy add pagination in Django, using Bootstrap's layout.
Home-page: https://github.com/staticdev/django-pagination-bootstrap
License: MIT
Author: staticdev
Author-email: staticdev-support@proton.me
Requires-Python: >=3.7.0,<4.0.0
Classifier: Development Status :: 7 - Inactive
Classifier: Environment :: Web Environment
Classifier: Framework :: Django
Classifier: Framework :: Django :: 2.0
Classifier: Framework :: Django :: 2.1
Classifier: Framework :: Django :: 2.2
Classifier: Framework :: Django :: 3.0
Classifier: Intended Audience :: Developers
Classifier: License :: OSI Approved :: MIT License
Classifier: Operating System :: OS Independent
Classifier: Programming Language :: Python
Classifier: Programming Language :: Python :: 3
Classifier: Programming Language :: Python :: 3.7
Classifier: Programming Language :: Python :: 3.8
Classifier: Programming Language :: Python :: 3.9
Classifier: Programming Language :: Python :: 3.10
Classifier: Programming Language :: Python :: 3.11
Classifier: Programming Language :: Python :: 3.6
Classifier: Programming Language :: Python :: 3.7
Classifier: Programming Language :: Python :: 3.8
Classifier: Programming Language :: Python :: 3.9
Classifier: Topic :: Internet :: WWW/HTTP
Classifier: Topic :: Internet :: WWW/HTTP :: Dynamic Content
Classifier: Topic :: Software Development :: Libraries :: Python Modules
Requires-Dist: django (>=2.0)
Project-URL: Changelog, https://github.com/staticdev/django-pagination-bootstrap/releases
Project-URL: Documentation, https://django-pagination-bootstrap.readthedocs.io
Project-URL: Repository, https://github.com/staticdev/django-pagination-bootstrap
